{
  "ai": {
    "type": "rb",
    "data": {}
  },
  "name": "Bird Keeper Wren",
  "textureResource": "rctmod:textures/trainers/single/type_flying.png",
  "team": [
    {
      "species": "fearow",
      "level": 94,
      "gender": "RANDOM",
      "nature": "docile",
      "ability": "keeneye",
      "ivs": {
        "hp": 12,
        "atk": 12,
        "def": 12,
        "spa": 12,
        "spd": 12,
        "spe": 12
      },
      "evs": {}
    },
    {
      "species": "dodrio",
      "level": 95,
      "gender": "RANDOM",
      "nature": "modest",
      "ability": "runaway",
      "ivs": {
        "hp": 12,
        "atk": 12,
        "def": 12,
        "spa": 12,
        "spd": 12,
        "spe": 12
      },
      "evs": {}
    },
    {
      "species": "talonflame",
      "level": 93,
      "gender": "RANDOM",
      "nature": "naive",
      "ability": "flamebody",
      "ivs": {
        "hp": 12,
        "atk": 12,
        "def": 12,
        "spa": 12,
        "spd": 12,
        "spe": 12
      },
      "evs": {}
    },
    {
      "species": "swellow",
      "level": 97,
      "gender": "RANDOM",
      "nature": "gentle",
      "ability": "guts",
      "ivs": {
        "hp": 12,
        "atk": 12,
        "def": 12,
        "spa": 12,
        "spd": 12,
        "spe": 12
      },
      "evs": {}
    }
  ]
}
