{
  "ai": {
    "data": {},
    "type": "rb"
  },
  "name": "Black Belt Takashi",
  "team": [
    {
      "ability": "noguard",
      "evs": {},
      "gender": "FEMALE",
      "heldItem": [
        "black_belt"
      ],
      "ivs": {
        "atk": 15,
        "def": 15,
        "hp": 15,
        "spa": 15,
        "spd": 15,
        "spe": 15
      },
      "level": 38,
      "moveset": [
        "vitalthrow",
        "wakeupslap",
        "dualchop",
        "submission"
      ],
      "nature": "careful",
      "species": "machoke"
    },
    {
      "ability": "noguard",
      "evs": {},
      "gender": "FEMALE",
      "heldItem": [
        "black_belt"
      ],
      "ivs": {
        "atk": 15,
        "def": 15,
        "hp": 15,
        "spa": 15,
        "spd": 15,
        "spe": 15
      },
      "level": 38,
      "moveset": [
        "wakeupslap",
        "dualchop",
        "submission",
        "bulkup"
      ],
      "nature": "sassy",
      "species": "machop"
    },
    {
      "ability": "noguard",
      "evs": {},
      "gender": "FEMALE",
      "heldItem": [
        "black_belt"
      ],
      "ivs": {
        "atk": 15,
        "def": 15,
        "hp": 15,
        "spa": 15,
        "spd": 15,
        "spe": 15
      },
      "level": 38,
      "moveset": [
        "vitalthrow",
        "wakeupslap",
        "dualchop",
        "submission"
      ],
      "nature": "lax",
      "species": "machoke"
    }
  ]
}
