{
  "ai": {
    "data": {},
    "type": "rb"
  },
  "name": "Pok\u00e9mon Ranger Kyler",
  "team": [
    {
      "ability": "chlorophyll",
      "evs": {},
      "gender": "MALE",
      "ivs": {},
      "level": 52,
      "moveset": [
        "worryseed",
        "leechseed",
        "gigadrain",
        "extrasensory"
      ],
      "nature": "modest",
      "species": "exeggcute"
    },
    {
      "ability": "guts",
      "evs": {},
      "gender": "FEMALE",
      "ivs": {},
      "level": 58,
      "moveset": [
        "scaryface",
        "rest",
        "snore",
        "thrash"
      ],
      "nature": "adamant",
      "species": "ursaring"
    }
  ]
}
