{
  "ai": {
    "data": {},
    "type": "rb"
  },
  "name": "Police Officer Danny",
  "team": [
    {
      "ability": "keeneye",
      "evs": {},
      "gender": "MALE",
      "ivs": {},
      "level": 38,
      "moveset": [
        "psychoshift",
        "airslash",
        "extrasensory",
        "roost"
      ],
      "nature": "timid",
      "species": "noctowl"
    },
    {
      "ability": "noguard",
      "evs": {},
      "gender": "MALE",
      "ivs": {},
      "level": 40,
      "moveset": [
        "leer",
        "lowsweep",
        "knockoff",
        "dualchop"
      ],
      "nature": "jolly",
      "species": "machoke"
    }
  ]
}
