{
  "ai": {
    "data": {},
    "type": "rb"
  },
  "name": "Swimmer\u2642 Matthew",
  "team": [
    {
      "ability": "damp",
      "evs": {},
      "gender": "FEMALE",
      "ivs": {
        "atk": 10,
        "def": 10,
        "hp": 10,
        "spa": 10,
        "spd": 10,
        "spe": 10
      },
      "level": 49,
      "moveset": [
        "mudshot",
        "bellydrum",
        "wakeupslap",
        "hydropump"
      ],
      "nature": "naive",
      "species": "poliwhirl"
    },
    {
      "ability": "damp",
      "evs": {},
      "gender": "FEMALE",
      "ivs": {
        "atk": 10,
        "def": 10,
        "hp": 10,
        "spa": 10,
        "spd": 10,
        "spe": 10
      },
      "level": 49,
      "moveset": [
        "bubblebeam",
        "hypnosis",
        "doubleslap",
        "dynamicpunch"
      ],
      "nature": "lonely",
      "species": "poliwrath"
    }
  ]
}
